{
  "product": {
    "id": 9444825563287,
    "title": "Realistic Licking Tongue Rose Vibrator for Women Nipples Clitoral Stimulation Vibrators Sex Toys for Adult Female Couples 18+",
    "handle": "realistic-licking-tongue-rose-vibrator-for-women-nipples-clitoral-stimulation-vibrators-sex-toys-for-adult-female-couples-18",
    "body_html": "<h1>SPECIFICATIONS</h1>\n<p><span>Brand Name</span>: <span style=\"color: #333;\">Xbonp</span></p>\n<p><span>Certification</span>: <span style=\"color: #333;\">CE</span></p>\n<p><span>Choice</span>: <span style=\"color: #333;\">yes</span></p>\n<p><span>Commodity Quality Certification</span>: <span style=\"color: #333;\">ce</span></p>\n<p><span>Feature 1</span>: <span style=\"color: #333;\">sex toy for women</span></p>\n<p><span>Feature 10</span>: <span style=\"color: #333;\">vibrator female</span></p>\n<p><span>Feature 11</span>: <span style=\"color: #333;\">egg masturbator</span></p>\n<p><span>Feature 12</span>: <span style=\"color: #333;\">Adult sex products</span></p>\n<p><span>Feature 13</span>: <span style=\"color: #333;\">sex toys for couples</span></p>\n<p><span>Feature 14</span>: <span style=\"color: #333;\">vagina simulator</span></p>\n<p><span>Feature 2</span>: <span style=\"color: #333;\">Vagina vibrators</span></p>\n<p><span>Feature 3</span>: <span style=\"color: #333;\">Vibrator for women</span></p>\n<p><span>Feature 4</span>: <span style=\"color: #333;\">Bullet vibrator</span></p>\n<p><span>Feature 5</span>: <span style=\"color: #333;\">Kegel balls</span></p>\n<p><span>Feature 6</span>: <span style=\"color: #333;\">vibrator for clitoris</span></p>\n<p><span>Feature 7</span>: <span style=\"color: #333;\">clitoris stimulator</span></p>\n<p><span>Feature 8</span>: <span style=\"color: #333;\">Remote control vibrating egg</span></p>\n<p><span>Feature 9</span>: <span style=\"color: #333;\">Vibrating egg</span></p>\n<p><span>Function</span>: <span style=\"color: #333;\">Manual Control</span></p>\n<p><span>High-concerned chemical</span>: <span style=\"color: #333;\">None</span></p>\n<p><span>Item Type</span>: <span style=\"color: #333;\">vibrators</span></p>\n<p><span>Material</span>: <span style=\"color: #333;\">Silicone</span></p>\n<p><span>Model Number</span>: <span style=\"color: #333;\">RF02</span></p>\n<p><span>Number of Pieces</span>: <span style=\"color: #333;\">One Unit</span></p>\n<p><span>Obscene Picture</span>: <span style=\"color: #333;\">No</span></p>\n<p><span>Origin</span>: <span style=\"color: #333;\">Mainland China</span></p>\n<p><span>Power Supply</span>: <span style=\"color: #333;\">Battery Powered</span></p>\n<p><span>Sexually Suggestive</span>: <span style=\"color: #333;\">No</span></p>\n<p><span>Size</span>: <span style=\"color: #333;\">as picture show</span></p>\n<p><span>Type</span>: <span style=\"color: #333;\">Lay on</span></p>\n<p><span>semi_Choice</span>: <span style=\"color: #333;\">yes</span></p>\n<div class=\"detailmodule_html\">\n<div class=\"detail-desc-decorate-richtext\">\n<div class=\"detailmodule_dynamic\"><strong><span style=\"font-size: 18px;\">Realistic Licking Tongue Rose Vibrator for Women Nipples Clitoral Stimulation Vibrators Sex Toys for Adult Female Couples 18+</span></strong></div>\n<div>\n<div>\n<p><strong><span style=\"font-size: 18px;\">About RF02</span></strong></p>\n<p><img src=\"https://ae01.alicdn.com/kf/S1b1807ea4dfe461284998583569c688bt.jpg\"><img src=\"https://ae01.alicdn.com/kf/S3468776eb2ba485fba5a62b0889127b8S.jpg\"><img src=\"https://ae01.alicdn.com/kf/Sa3467f3079274d4da930e5eab97e9630T.jpg\"><img src=\"https://ae01.alicdn.com/kf/Sf0b91685623b477d9f53bf65fa968a4fT.jpg\"><img src=\"https://ae01.alicdn.com/kf/S7dfb50c49dc84092994493c356f3df7aQ.jpg?width=1000&amp;height=1332&amp;hash=2332\"></p>\n<div>\n<div>\n<p><strong><span style=\"font-size: 18px;\">About RF10</span></strong></p>\n<p><img src=\"https://ae01.alicdn.com/kf/S585c35b453c445fd8e8d21e3c8193f03Q.jpg\"><img src=\"https://ae01.alicdn.com/kf/S389b8352adba43028c3cedd0848ab943b.jpg\"><img src=\"https://ae01.alicdn.com/kf/Sb3907f513562431cb9f463f1d7f5737bg.jpg\"><img src=\"https://ae01.alicdn.com/kf/S4c22549ac9374243b1b84fba5532f87f0.jpg\"><img src=\"https://ae01.alicdn.com/kf/S4146aa1f35f34f9ca00f417b307a96b9w.jpg\"><img src=\"https://ae01.alicdn.com/kf/S79e6929123d244208b41d008bb58f474n.jpg?width=1000&amp;height=1332&amp;hash=2332\"><img src=\"https://ae01.alicdn.com/kf/S323b2ce36cb54faaa8b68112408f87c5j.jpg?width=1000&amp;height=2405&amp;hash=3405\"></p>\n</div>\n</div>\n<div style=\"font-family: 'TT Norms Pro', 'Open Sans', Roboto, Arial, Helvetica, sans-serif, SimSun; font-size: 14px; font-weight: 400; letter-spacing: normal; text-align: start; white-space: normal; color: rgb(34, 34, 34); background-color: rgb(255, 255, 255); margin: 0px; padding: 0px; box-sizing: content-box;\" class=\"detailmodule_text\" align=\"start\"><br></div>\n<div><br></div>\n</div>\n</div>\n<div><br></div>\n</div>\n</div>\n<p><br></p>",
    "published_at": "2026-02-01T23:07:52-06:00",
    "created_at": "2026-02-01T19:26:31-06:00",
    "updated_at": "2026-02-02T16:35:05-06:00",
    "vendor": "OVA",
    "product_type": "",
    "tags": [],
    "variants": [
      {
        "id": 46870069346455,
        "title": "RF10-SK",
        "option1": "RF10-SK",
        "option2": null,
        "option3": null,
        "sku": "14:29#RF10-SK",
        "requires_shipping": true,
        "taxable": false,
        "featured_image": {
          "id": 50936660590743,
          "product_id": 9444825563287,
          "position": 20,
          "created_at": "2026-02-01T19:26:32-06:00",
          "updated_at": "2026-02-01T19:26:34-06:00",
          "alt": null,
          "width": 1000,
          "height": 1000,
          "src": "https://cdn.shopify.com/s/files/1/0708/3435/6375/files/S4146aa1f35f34f9ca00f417b307a96b9w.webp?v=1769995594",
          "variant_ids": [
            46870069346455
          ]
        },
        "available": true,
        "price": "30.00",
        "grams": 200,
        "compare_at_price": "11.07",
        "position": 1,
        "product_id": 9444825563287,
        "created_at": "2026-02-01T19:26:32-06:00",
        "updated_at": "2026-02-02T16:35:05-06:00"
      },
      {
        "id": 46870069379223,
        "title": "RF10-SK-BOX",
        "option1": "RF10-SK-BOX",
        "option2": null,
        "option3": null,
        "sku": "14:6144#RF10-SK-BOX",
        "requires_shipping": true,
        "taxable": false,
        "featured_image": {
          "id": 50936660623511,
          "product_id": 9444825563287,
          "position": 21,
          "created_at": "2026-02-01T19:26:32-06:00",
          "updated_at": "2026-02-01T19:26:34-06:00",
          "alt": null,
          "width": 1000,
          "height": 1000,
          "src": "https://cdn.shopify.com/s/files/1/0708/3435/6375/files/S44447488c18b4e468a565041fa4bee45g.webp?v=1769995594",
          "variant_ids": [
            46870069379223
          ]
        },
        "available": true,
        "price": "34.00",
        "grams": 200,
        "compare_at_price": "11.89",
        "position": 2,
        "product_id": 9444825563287,
        "created_at": "2026-02-01T19:26:32-06:00",
        "updated_at": "2026-02-02T16:35:05-06:00"
      },
      {
        "id": 46870069411991,
        "title": "RF02",
        "option1": "RF02",
        "option2": null,
        "option3": null,
        "sku": "14:6994332#RF02",
        "requires_shipping": true,
        "taxable": false,
        "featured_image": {
          "id": 50936660525207,
          "product_id": 9444825563287,
          "position": 18,
          "created_at": "2026-02-01T19:26:32-06:00",
          "updated_at": "2026-02-01T19:26:34-06:00",
          "alt": null,
          "width": 1000,
          "height": 1000,
          "src": "https://cdn.shopify.com/s/files/1/0708/3435/6375/files/S23a09b7c5adb45618492c442ca22b91ab.webp?v=1769995594",
          "variant_ids": [
            46870069411991
          ]
        },
        "available": true,
        "price": "38.00",
        "grams": 200,
        "compare_at_price": "18.18",
        "position": 3,
        "product_id": 9444825563287,
        "created_at": "2026-02-01T19:26:32-06:00",
        "updated_at": "2026-02-02T16:35:05-06:00"
      },
      {
        "id": 46870069444759,
        "title": "RF02-Box",
        "option1": "RF02-Box",
        "option2": null,
        "option3": null,
        "sku": "14:200013901#RF02-Box",
        "requires_shipping": true,
        "taxable": false,
        "featured_image": {
          "id": 50936660557975,
          "product_id": 9444825563287,
          "position": 19,
          "created_at": "2026-02-01T19:26:32-06:00",
          "updated_at": "2026-02-01T19:26:34-06:00",
          "alt": null,
          "width": 1000,
          "height": 1000,
          "src": "https://cdn.shopify.com/s/files/1/0708/3435/6375/files/S0f18df0a47f74c49a9bb87097627c0dbA.webp?v=1769995594",
          "variant_ids": [
            46870069444759
          ]
        },
        "available": true,
        "price": "40.00",
        "grams": 200,
        "compare_at_price": "18.91",
        "position": 4,
        "product_id": 9444825563287,
        "created_at": "2026-02-01T19:26:32-06:00",
        "updated_at": "2026-02-02T16:35:05-06:00"
      }
    ],
    "images": [
      {
        "id": 50936659968151,
        "created_at": "2026-02-01T19:26:32-06:00",
        "position": 1,
        "updated_at": "2026-02-01T19:26:34-06:00",
        "product_id": 9444825563287,
        "variant_ids": [],
        "src": "https://cdn.shopify.com/s/files/1/0708/3435/6375/files/S3b700501ae1b4fd0a29c9fb154f6abe0y.webp?v=1769995594",
        "width": 1000,
        "height": 1000
      },
      {
        "id": 50936660000919,
        "created_at": "2026-02-01T19:26:32-06:00",
        "position": 2,
        "updated_at": "2026-02-01T19:26:33-06:00",
        "product_id": 9444825563287,
        "variant_ids": [],
        "src": "https://cdn.shopify.com/s/files/1/0708/3435/6375/files/Sca662c4accfb49918a1267abb5f02d4eA.webp?v=1769995593",
        "width": 1000,
        "height": 1000
      },
      {
        "id": 50936660033687,
        "created_at": "2026-02-01T19:26:32-06:00",
        "position": 3,
        "updated_at": "2026-02-01T19:26:34-06:00",
        "product_id": 9444825563287,
        "variant_ids": [],
        "src": "https://cdn.shopify.com/s/files/1/0708/3435/6375/files/S2246e77a38894965a21439732be34413F.webp?v=1769995594",
        "width": 1000,
        "height": 1000
      },
      {
        "id": 50936660066455,
        "created_at": "2026-02-01T19:26:32-06:00",
        "position": 4,
        "updated_at": "2026-02-01T19:26:34-06:00",
        "product_id": 9444825563287,
        "variant_ids": [],
        "src": "https://cdn.shopify.com/s/files/1/0708/3435/6375/files/S4eeba808de0142d4bbdb58dc0a50db515.webp?v=1769995594",
        "width": 1000,
        "height": 1000
      },
      {
        "id": 50936660099223,
        "created_at": "2026-02-01T19:26:32-06:00",
        "position": 5,
        "updated_at": "2026-02-01T19:26:33-06:00",
        "product_id": 9444825563287,
        "variant_ids": [],
        "src": "https://cdn.shopify.com/s/files/1/0708/3435/6375/files/Sa963089b95544609b291bbbb386bfa83R.webp?v=1769995593",
        "width": 1000,
        "height": 1000
      },
      {
        "id": 50936660131991,
        "created_at": "2026-02-01T19:26:32-06:00",
        "position": 6,
        "updated_at": "2026-02-01T19:26:34-06:00",
        "product_id": 9444825563287,
        "variant_ids": [],
        "src": "https://cdn.shopify.com/s/files/1/0708/3435/6375/files/Sc6ac3b72d0f34d088147f9246ee85570Q.webp?v=1769995594",
        "width": 1000,
        "height": 1000
      },
      {
        "id": 50936660164759,
        "created_at": "2026-02-01T19:26:32-06:00",
        "position": 7,
        "updated_at": "2026-02-01T19:26:34-06:00",
        "product_id": 9444825563287,
        "variant_ids": [],
        "src": "https://cdn.shopify.com/s/files/1/0708/3435/6375/files/S1b1807ea4dfe461284998583569c688bt.webp?v=1769995594",
        "width": 1000,
        "height": 1000
      },
      {
        "id": 50936660197527,
        "created_at": "2026-02-01T19:26:32-06:00",
        "position": 8,
        "updated_at": "2026-02-01T19:26:34-06:00",
        "product_id": 9444825563287,
        "variant_ids": [],
        "src": "https://cdn.shopify.com/s/files/1/0708/3435/6375/files/S3468776eb2ba485fba5a62b0889127b8S.webp?v=1769995594",
        "width": 1000,
        "height": 1000
      },
      {
        "id": 50936660230295,
        "created_at": "2026-02-01T19:26:32-06:00",
        "position": 9,
        "updated_at": "2026-02-01T19:26:34-06:00",
        "product_id": 9444825563287,
        "variant_ids": [],
        "src": "https://cdn.shopify.com/s/files/1/0708/3435/6375/files/Sa3467f3079274d4da930e5eab97e9630T.webp?v=1769995594",
        "width": 1000,
        "height": 1000
      },
      {
        "id": 50936660263063,
        "created_at": "2026-02-01T19:26:32-06:00",
        "position": 10,
        "updated_at": "2026-02-01T19:26:33-06:00",
        "product_id": 9444825563287,
        "variant_ids": [],
        "src": "https://cdn.shopify.com/s/files/1/0708/3435/6375/files/Sf0b91685623b477d9f53bf65fa968a4fT.webp?v=1769995593",
        "width": 1000,
        "height": 1000
      },
      {
        "id": 50936660295831,
        "created_at": "2026-02-01T19:26:32-06:00",
        "position": 11,
        "updated_at": "2026-02-01T19:26:33-06:00",
        "product_id": 9444825563287,
        "variant_ids": [],
        "src": "https://cdn.shopify.com/s/files/1/0708/3435/6375/files/S7dfb50c49dc84092994493c356f3df7aQ.webp?v=1769995593",
        "width": 1000,
        "height": 1332
      },
      {
        "id": 50936660328599,
        "created_at": "2026-02-01T19:26:32-06:00",
        "position": 12,
        "updated_at": "2026-02-01T19:26:34-06:00",
        "product_id": 9444825563287,
        "variant_ids": [],
        "src": "https://cdn.shopify.com/s/files/1/0708/3435/6375/files/S585c35b453c445fd8e8d21e3c8193f03Q.webp?v=1769995594",
        "width": 1340,
        "height": 1785
      },
      {
        "id": 50936660361367,
        "created_at": "2026-02-01T19:26:32-06:00",
        "position": 13,
        "updated_at": "2026-02-01T19:26:34-06:00",
        "product_id": 9444825563287,
        "variant_ids": [],
        "src": "https://cdn.shopify.com/s/files/1/0708/3435/6375/files/S389b8352adba43028c3cedd0848ab943b.webp?v=1769995594",
        "width": 1340,
        "height": 1785
      },
      {
        "id": 50936660394135,
        "created_at": "2026-02-01T19:26:32-06:00",
        "position": 14,
        "updated_at": "2026-02-01T19:26:34-06:00",
        "product_id": 9444825563287,
        "variant_ids": [],
        "src": "https://cdn.shopify.com/s/files/1/0708/3435/6375/files/Sb3907f513562431cb9f463f1d7f5737bg.webp?v=1769995594",
        "width": 1340,
        "height": 1785
      },
      {
        "id": 50936660426903,
        "created_at": "2026-02-01T19:26:32-06:00",
        "position": 15,
        "updated_at": "2026-02-01T19:26:34-06:00",
        "product_id": 9444825563287,
        "variant_ids": [],
        "src": "https://cdn.shopify.com/s/files/1/0708/3435/6375/files/S4c22549ac9374243b1b84fba5532f87f0.webp?v=1769995594",
        "width": 1340,
        "height": 1785
      },
      {
        "id": 50936660459671,
        "created_at": "2026-02-01T19:26:32-06:00",
        "position": 16,
        "updated_at": "2026-02-01T19:26:34-06:00",
        "product_id": 9444825563287,
        "variant_ids": [],
        "src": "https://cdn.shopify.com/s/files/1/0708/3435/6375/files/S79e6929123d244208b41d008bb58f474n.webp?v=1769995594",
        "width": 1000,
        "height": 1332
      },
      {
        "id": 50936660492439,
        "created_at": "2026-02-01T19:26:32-06:00",
        "position": 17,
        "updated_at": "2026-02-01T19:26:33-06:00",
        "product_id": 9444825563287,
        "variant_ids": [],
        "src": "https://cdn.shopify.com/s/files/1/0708/3435/6375/files/S323b2ce36cb54faaa8b68112408f87c5j.webp?v=1769995593",
        "width": 1000,
        "height": 2405
      },
      {
        "id": 50936660525207,
        "created_at": "2026-02-01T19:26:32-06:00",
        "position": 18,
        "updated_at": "2026-02-01T19:26:34-06:00",
        "product_id": 9444825563287,
        "variant_ids": [
          46870069411991
        ],
        "src": "https://cdn.shopify.com/s/files/1/0708/3435/6375/files/S23a09b7c5adb45618492c442ca22b91ab.webp?v=1769995594",
        "width": 1000,
        "height": 1000
      },
      {
        "id": 50936660557975,
        "created_at": "2026-02-01T19:26:32-06:00",
        "position": 19,
        "updated_at": "2026-02-01T19:26:34-06:00",
        "product_id": 9444825563287,
        "variant_ids": [
          46870069444759
        ],
        "src": "https://cdn.shopify.com/s/files/1/0708/3435/6375/files/S0f18df0a47f74c49a9bb87097627c0dbA.webp?v=1769995594",
        "width": 1000,
        "height": 1000
      },
      {
        "id": 50936660590743,
        "created_at": "2026-02-01T19:26:32-06:00",
        "position": 20,
        "updated_at": "2026-02-01T19:26:34-06:00",
        "product_id": 9444825563287,
        "variant_ids": [
          46870069346455
        ],
        "src": "https://cdn.shopify.com/s/files/1/0708/3435/6375/files/S4146aa1f35f34f9ca00f417b307a96b9w.webp?v=1769995594",
        "width": 1000,
        "height": 1000
      },
      {
        "id": 50936660623511,
        "created_at": "2026-02-01T19:26:32-06:00",
        "position": 21,
        "updated_at": "2026-02-01T19:26:34-06:00",
        "product_id": 9444825563287,
        "variant_ids": [
          46870069379223
        ],
        "src": "https://cdn.shopify.com/s/files/1/0708/3435/6375/files/S44447488c18b4e468a565041fa4bee45g.webp?v=1769995594",
        "width": 1000,
        "height": 1000
      }
    ],
    "options": [
      {
        "name": "Color",
        "position": 1,
        "values": [
          "RF10-SK",
          "RF10-SK-BOX",
          "RF02",
          "RF02-Box"
        ]
      }
    ]
  }
}